pull_the_pitcher/__init__.py
pull_the_pitcher/_nbdev.py
pull_the_pitcher/inference.py
pull_the_pitcher/metrics.py
pull_the_pitcher/utils.py
pull_the_pitcher/data/__init__.py
pull_the_pitcher/data/acquisition.py
pull_the_pitcher/data/pipeline.py
pull_the_pitcher/data/processing.py
pull_the_pitcher-0.1.14.dist-info/LICENSE
pull_the_pitcher-0.1.14.dist-info/METADATA
pull_the_pitcher-0.1.14.dist-info/WHEEL
pull_the_pitcher-0.1.14.dist-info/entry_points.txt
pull_the_pitcher-0.1.14.dist-info/top_level.txt
pull_the_pitcher-0.1.14.dist-info/RECORD
