Metadata-Version: 2.1
Name: pull-the-pitcher
Version: 0.1.14
Summary: Predicting when AL managers will remove their starting pitchers.
Home-page: https://github.com/collinprather/pull_the_pitcher/tree/master/
Author: Collin Prather
Author-email: collin.prather742@gmail.com
License: Apache Software License 2.0
Keywords: MLB analytics deep-learning python
Platform: UNKNOWN
Classifier: Development Status :: 3 - Alpha
Classifier: Intended Audience :: Developers
Classifier: License :: OSI Approved :: Apache Software License
Classifier: Natural Language :: English
Classifier: Programming Language :: Python :: 3.6
Classifier: Programming Language :: Python :: 3.7
Classifier: Programming Language :: Python :: 3.8
Requires-Python: >=3.6
Requires-Dist: pybaseball (==1.0.8)
Requires-Dist: pandas (==1.0.3)
Requires-Dist: scikit-learn (==0.22.1)
Requires-Dist: seaborn (==0.9.0)
Requires-Dist: matplotlib (==3.1.1)
Requires-Dist: torch (==1.3.1)
Requires-Dist: pytest (==5.4.1)
Requires-Dist: streamlit (==0.63.1)
Requires-Dist: nbdev (==0.2.18)
Requires-Dist: pull-the-pitcher
Requires-Dist: drsa
Requires-Dist: altair (==4.1.0)
